vpn_exclude_sbs/__init__.py
vpn_exclude_sbs/__main__.py
vpn_exclude_sbs/utilities.py
vpn_exclude_sbs-0.2.0.dist-info/LICENCE
vpn_exclude_sbs-0.2.0.dist-info/METADATA
vpn_exclude_sbs-0.2.0.dist-info/WHEEL
vpn_exclude_sbs-0.2.0.dist-info/top_level.txt
vpn_exclude_sbs-0.2.0.dist-info/RECORD
